discco/__init__.py
discco/discco.py
discco-0.2.7.dist-info/LICENSE
discco-0.2.7.dist-info/METADATA
discco-0.2.7.dist-info/WHEEL
discco-0.2.7.dist-info/top_level.txt
discco-0.2.7.dist-info/RECORD
