Metadata-Version: 2.1
Name: discco
Version: 0.2.7
Summary: Quantification of membrane and cytoplasmic concentrations based on differentiable simulation of cell cortex images
Author-email: Tom Bland <tom_bland@hotmail.co.uk>
License: Attribution 4.0 International
Project-URL: Source, https://github.com/tsmbland/discco
License-File: LICENSE
Requires-Dist: numpy
Requires-Dist: matplotlib
Requires-Dist: pandas
Requires-Dist: tqdm
Requires-Dist: jax
Requires-Dist: optax
Requires-Dist: scikit-image
Requires-Dist: par-segmentation >=0.1.12
Provides-Extra: dev
Requires-Dist: pre-commit ; extra == 'dev'
Requires-Dist: black ; extra == 'dev'
Requires-Dist: pip-tools ; extra == 'dev'
